mmapds.cpython-36m-x86_64-linux-gnu.so
mmapds-0.0.2.dist-info/RECORD
mmapds-0.0.2.dist-info/METADATA
mmapds-0.0.2.dist-info/top_level.txt
mmapds-0.0.2.dist-info/WHEEL
mmapds-0.0.2.dist-info/LICENSE
